pydux/__init__.py
pydux/apply_middleware.py
pydux/combine_reducers.py
pydux/compose.py
pydux/create_store.py
pydux/extend.py
pydux/log_middleware.py
pydux/thunk_middleware.py
pydux-0.2.2.dist-info/DESCRIPTION.rst
pydux-0.2.2.dist-info/METADATA
pydux-0.2.2.dist-info/RECORD
pydux-0.2.2.dist-info/WHEEL
pydux-0.2.2.dist-info/metadata.json
pydux-0.2.2.dist-info/top_level.txt
