Metadata-Version: 2.0
Name: pydux
Version: 0.2.2
Summary: Python + Redux = Pydux
Home-page: http://github.com/usrlocalben/pydux/
Author: Benjamin Yates
Author-email: benjamin@rqdq.com
License: MIT
Platform: UNKNOWN
